{"dependencies":[],"generated":{"js":"\"use strict\";\n\nObject.defineProperty(exports, \"__esModule\", {\n  value: true\n});\nexports.default = {\n  search: function (searchTerm, searchLimit, sortBy) {\n    return fetch(`http://www.reddit.com/search.json?q=${searchTerm}&${sortBy}&limit=${searchLimit}`).then(res => res.json()).then(data => data.data.children.map(data => data.data)).catch(err => console.log(err));\n  }\n};","map":{"mappings":[{"generated":{"line":6,"column":18},"source":"redditapi.js","original":{"line":1,"column":15}},{"name":"search","generated":{"line":7,"column":0},"source":"redditapi.js","original":{"line":2,"column":2}},{"generated":{"line":7,"column":10},"source":"redditapi.js","original":{"line":2,"column":10}},{"name":"searchTerm","generated":{"line":7,"column":20},"source":"redditapi.js","original":{"line":2,"column":19}},{"generated":{"line":7,"column":30},"source":"redditapi.js","original":{"line":2,"column":10}},{"name":"searchLimit","generated":{"line":7,"column":32},"source":"redditapi.js","original":{"line":2,"column":31}},{"generated":{"line":7,"column":43},"source":"redditapi.js","original":{"line":2,"column":10}},{"name":"sortBy","generated":{"line":7,"column":45},"source":"redditapi.js","original":{"line":2,"column":44}},{"generated":{"line":7,"column":51},"source":"redditapi.js","original":{"line":2,"column":10}},{"generated":{"line":7,"column":53},"source":"redditapi.js","original":{"line":2,"column":52}},{"generated":{"line":8,"column":0},"source":"redditapi.js","original":{"line":3,"column":4}},{"name":"fetch","generated":{"line":8,"column":11},"source":"redditapi.js","original":{"line":3,"column":11}},{"generated":{"line":8,"column":17},"source":"redditapi.js","original":{"line":3,"column":18}},{"name":"searchTerm","generated":{"line":8,"column":56},"source":"redditapi.js","original":{"line":3,"column":56}},{"generated":{"line":8,"column":66},"source":"redditapi.js","original":{"line":3,"column":67}},{"name":"sortBy","generated":{"line":8,"column":70},"source":"redditapi.js","original":{"line":3,"column":70}},{"generated":{"line":8,"column":76},"source":"redditapi.js","original":{"line":3,"column":77}},{"name":"searchLimit","generated":{"line":8,"column":86},"source":"redditapi.js","original":{"line":3,"column":86}},{"generated":{"line":8,"column":97},"source":"redditapi.js","original":{"line":3,"column":98}},{"generated":{"line":8,"column":99},"source":"redditapi.js","original":{"line":3,"column":11}},{"name":"then","generated":{"line":8,"column":101},"source":"redditapi.js","original":{"line":4,"column":5}},{"generated":{"line":8,"column":105},"source":"redditapi.js","original":{"line":3,"column":11}},{"name":"res","generated":{"line":8,"column":106},"source":"redditapi.js","original":{"line":4,"column":10}},{"name":"res","generated":{"line":8,"column":113},"source":"redditapi.js","original":{"line":4,"column":17}},{"name":"json","generated":{"line":8,"column":117},"source":"redditapi.js","original":{"line":4,"column":21}},{"generated":{"line":8,"column":121},"source":"redditapi.js","original":{"line":4,"column":17}},{"generated":{"line":8,"column":123},"source":"redditapi.js","original":{"line":3,"column":11}},{"name":"then","generated":{"line":8,"column":125},"source":"redditapi.js","original":{"line":5,"column":5}},{"generated":{"line":8,"column":129},"source":"redditapi.js","original":{"line":3,"column":11}},{"name":"data","generated":{"line":8,"column":130},"source":"redditapi.js","original":{"line":5,"column":10}},{"name":"data","generated":{"line":8,"column":138},"source":"redditapi.js","original":{"line":5,"column":18}},{"name":"data","generated":{"line":8,"column":143},"source":"redditapi.js","original":{"line":5,"column":23}},{"generated":{"line":8,"column":147},"source":"redditapi.js","original":{"line":5,"column":18}},{"name":"children","generated":{"line":8,"column":148},"source":"redditapi.js","original":{"line":5,"column":28}},{"generated":{"line":8,"column":156},"source":"redditapi.js","original":{"line":5,"column":18}},{"name":"map","generated":{"line":8,"column":157},"source":"redditapi.js","original":{"line":5,"column":37}},{"generated":{"line":8,"column":160},"source":"redditapi.js","original":{"line":5,"column":18}},{"name":"data","generated":{"line":8,"column":161},"source":"redditapi.js","original":{"line":5,"column":41}},{"name":"data","generated":{"line":8,"column":169},"source":"redditapi.js","original":{"line":5,"column":49}},{"name":"data","generated":{"line":8,"column":174},"source":"redditapi.js","original":{"line":5,"column":54}},{"generated":{"line":8,"column":178},"source":"redditapi.js","original":{"line":5,"column":18}},{"generated":{"line":8,"column":179},"source":"redditapi.js","original":{"line":3,"column":11}},{"name":"catch","generated":{"line":8,"column":181},"source":"redditapi.js","original":{"line":6,"column":5}},{"generated":{"line":8,"column":186},"source":"redditapi.js","original":{"line":3,"column":11}},{"name":"err","generated":{"line":8,"column":187},"source":"redditapi.js","original":{"line":6,"column":11}},{"name":"console","generated":{"line":8,"column":194},"source":"redditapi.js","original":{"line":6,"column":18}},{"name":"log","generated":{"line":8,"column":202},"source":"redditapi.js","original":{"line":6,"column":26}},{"generated":{"line":8,"column":205},"source":"redditapi.js","original":{"line":6,"column":18}},{"name":"err","generated":{"line":8,"column":206},"source":"redditapi.js","original":{"line":6,"column":30}},{"generated":{"line":8,"column":209},"source":"redditapi.js","original":{"line":6,"column":18}},{"generated":{"line":8,"column":210},"source":"redditapi.js","original":{"line":3,"column":11}},{"generated":{"line":8,"column":211},"source":"redditapi.js","original":{"line":3,"column":4}},{"generated":{"line":9,"column":0},"source":"redditapi.js","original":{"line":7,"column":3}},{"generated":{"line":10,"column":0},"source":"redditapi.js","original":{"line":1,"column":15}}],"sources":{"redditapi.js":"export default {\n  search: function(searchTerm, searchLimit, sortBy) {\n    return fetch(`http://www.reddit.com/search.json?q=${searchTerm}&${sortBy}&limit=${searchLimit}`)\n    .then(res => res.json())\n    .then(data => data.data.children.map(data => data.data))\n    .catch(err => console.log(err));\n  }\n}\n"},"lineCount":null}},"hash":"a530d0f16b2d7a6a107e41dbf2dc5fce","cacheData":{"env":{}}}